################################################################################

################################################################################

<item>
<title>[B][COLORorange]TANKS[/COLOR][/B]</title>
<link>//</link>
</item>

<dir>
  <title>SNT</title>
  <link>https://raw.githubusercontent.com/PiDiaries/wow/master/Overwatchleague/players/SNT.xml</link>
  <thumbnail></thumbnail>
  <fanart></fanart>
  <summary></summary>
</dir>


<dir>
  <title>XepheR</title>
  <link>https://raw.githubusercontent.com/PiDiaries/wow/master/Overwatchleague/players/XepheR.xml</link>
  <thumbnail></thumbnail>
  <fanart></fanart>
  <summary></summary>
</dir>

<dir>
  <title>Swon</title>
  <link>https://raw.githubusercontent.com/PiDiaries/wow/master/Overwatchleague/players/Swon.xml</link>
  <thumbnail></thumbnail>
  <fanart></fanart>
  <summary></summary>
</dir>


<item>
<title>[B][COLORorange]DPS[/COLOR][/B]</title>
<link>//</link>
</item>

<dir>
  <title>TviQ</title>
  <link>https://raw.githubusercontent.com/PiDiaries/wow/master/Overwatchleague/players/TviQ.xml</link>
  <thumbnail>https://bnetcmsus-a.akamaihd.net/cms/page_media/L76ZWRFRYTN21512685744749.png</thumbnail>
  <fanart>https://i.imgur.com/dXG90Xd.png</fanart>
  <summary>Kevyn "TviQ" Lindström is a Swedish player currently playing for the Florida Mayhem. He is most famous for his flexibility, being one of the earliest DPS players to have a deep hero pool.</summary>
</dir>

<dir>
  <title>Sayaplayer</title>
  <link>https://raw.githubusercontent.com/PiDiaries/wow/master/Overwatchleague/players/Sayaplayer.xml</link>
  <thumbnail></thumbnail>
  <fanart></fanart>
  <summary></summary>
</dir>

<dir>
  <title>BQB</title>
  <link>https://raw.githubusercontent.com/PiDiaries/wow/master/Overwatchleague/players/BQB.xml</link>
  <thumbnail></thumbnail>
  <fanart></fanart>
  <summary></summary>
</dir>

<dir>
  <title>Apply</title>
  <link>https://raw.githubusercontent.com/PiDiaries/wow/master/Overwatchleague/players/Apply.xml</link>
  <thumbnail></thumbnail>
  <fanart></fanart>
  <summary></summary>
</dir>


<item>
<title>[B][COLORorange]SUPPORT[/COLOR][/B]</title>
<link>//</link>
</item>

<dir>
  <title>HaGoPeun</title>
  <link>https://raw.githubusercontent.com/PiDiaries/wow/master/Overwatchleague/players/HaGoPeun.xml</link>
  <thumbnail></thumbnail>
  <fanart></fanart>
  <summary></summary>
</dir>

<dir>
  <title>Kris</title>
  <link>https://raw.githubusercontent.com/PiDiaries/wow/master/Overwatchleague/players/Kris.xml</link>
  <thumbnail></thumbnail>
  <fanart></fanart>
  <summary></summary>
</dir>