
<plugin>
  <title>Gob</title>
  <link>
  <sublink>plugin://plugin.video.twitch/?use_player=True&channel_id=xxxxxx&mode=play (Live Link)</sublink>
  <sublink>plugin://plugin.video.twitch/?use_player=True&channel_id=xxxxxx&amp;mode=channel_videos (VODs)</sublink>
  </link>
  <summary>Gabriel Boylan</summary>
</plugin>

<plugin>
  <title>termo</title>
  <link>
  <sublink>plugin://plugin.video.twitch/?use_player=True&channel_id=xxxxxx&mode=play (Live Link)</sublink>
  <sublink>plugin://plugin.video.twitch/?use_player=True&channel_id=xxxxxx&amp;mode=channel_videos (VODs)</sublink>
  </link>
  <summary>Jake Hickman</summary>
</plugin>

<plugin>
  <title>usmc</title>
  <link>
  <sublink>plugin://plugin.video.twitch/?use_player=True&channel_id=xxxxxx&mode=play (Live Link)</sublink>
  <sublink>plugin://plugin.video.twitch/?use_player=True&channel_id=xxxxxx&amp;mode=channel_videos (VODs)</sublink>
  </link>
  <summary>Ahmad Rahhal</summary>
</plugin>

<plugin>
  <title>xZoL</title>
  <link>
  <sublink>plugin://plugin.video.twitch/?use_player=True&channel_id=xxxxxx&mode=play (Live Link)</sublink>
  <sublink>plugin://plugin.video.twitch/?use_player=True&channel_id=xxxxxx&amp;mode=channel_videos (VODs)</sublink>
  </link>
  <summary>Marcus Jacob</summary>
</plugin>

<plugin>
  <title>Project</title>
  <link>
  <sublink>plugin://plugin.video.twitch/?use_player=True&channel_id=xxxxxx&mode=play (Live Link)</sublink>
  <sublink>plugin://plugin.video.twitch/?use_player=True&channel_id=xxxxxx&amp;mode=channel_videos (VODs)</sublink>
  </link>
  <summary>Nicholas O'Brien</summary>
</plugin>

<plugin>
  <title>Eevee</title>
  <link>
  <sublink>plugin://plugin.video.twitch/?use_player=True&channel_id=xxxxxx&mode=play (Live Link)</sublink>
  <sublink>plugin://plugin.video.twitch/?use_player=True&channel_id=xxxxxx&amp;mode=channel_videos (VODs)</sublink>
  </link>
  <summary>Jasmine Scott</summary>
</plugin>

<plugin>
  <title>Muni</title>
  <link>
  <sublink>plugin://plugin.video.twitch/?use_player=True&channel_id=xxxxxx&mode=play (Live Link)</sublink>
  <sublink>plugin://plugin.video.twitch/?use_player=True&channel_id=xxxxxx&amp;mode=channel_videos (VODs)</sublink>
  </link>
  <summary>George Arritidis</summary>
</plugin>
