
<plugin>
  <title>Kura</title>
  <link>
  <sublink>plugin://plugin.video.twitch/?use_player=True&channel_id=xxxxxx&mode=play (Live Link)</sublink>
  <sublink>plugin://plugin.video.twitch/?channel_id=xxxxxx&amp;mode=channel_videos (VODs)</sublink>
  </link>
  <summary>Sean Kovacs</summary>
</plugin>

<plugin>
  <title>Roro</title>
  <link>
  <sublink>plugin://plugin.video.twitch/?use_player=True&channel_id=xxxxxx&mode=play (Live Link)</sublink>
  <sublink>plugin://plugin.video.twitch/?channel_id=xxxxxx&amp;mode=channel_videos (VODs)</sublink>
  </link>
  <summary>Rowan Goldsmith</summary>
</plugin>

<plugin>
  <title>Tongue</title>
  <link>
  <sublink>plugin://plugin.video.twitch/?use_player=True&channel_id=xxxxxx&mode=play (Live Link)</sublink>
  <sublink>plugin://plugin.video.twitch/?channel_id=xxxxxx&amp;mode=channel_videos (VODs)</sublink>
  </link>
  <summary>Giorgio Lahdo</summary>
</plugin>

<plugin>
  <title>Knellery</title>
  <link>
  <sublink>plugin://plugin.video.twitch/?use_player=True&channel_id=xxxxxx&mode=play (Live Link)</sublink>
  <sublink>plugin://plugin.video.twitch/?channel_id=xxxxxx&amp;mode=channel_videos (VODs)</sublink>
  </link>
  <summary>Joshua Knell</summary>
</plugin>

<plugin>
  <title>tails</title>
  <link>
  <sublink>plugin://plugin.video.twitch/?use_player=True&channel_id=xxxxxx&mode=play (Live Link)</sublink>
  <sublink>plugin://plugin.video.twitch/?channel_id=xxxxxx&amp;mode=channel_videos (VODs)</sublink>
  </link>
  <summary>Mitchell Burnett</summary>
</plugin>

<plugin>
  <title>Nozz</title>
  <link>
  <sublink>plugin://plugin.video.twitch/?use_player=True&channel_id=xxxxxx&mode=play (Live Link)</sublink>
  <sublink>plugin://plugin.video.twitch/?channel_id=xxxxxx&amp;mode=channel_videos (VODs)</sublink>
  </link>
  <summary>Noah McClafferty</summary>
</plugin>

<plugin>
  <title>Bryce</title>
  <link>
  <sublink>plugin://plugin.video.twitch/?use_player=True&channel_id=xxxxxx&mode=play (Live Link)</sublink>
  <sublink>plugin://plugin.video.twitch/?channel_id=xxxxxx&amp;mode=channel_videos (VODs)</sublink>
  </link>
  <summary>David Bryce Williams</summary>
</plugin>
