##########################################################################################

###########################################################################################

<plugin>
  <title>Gesture</title>
  <twitch>t/170974282</twitch>>
  <thumbnail>https://bnetcmsus-a.akamaihd.net/cms/page_media/SMHDMNUINHC51512776037290.png</thumbnail>
  <summary>Hong Jae-hee (홍재희)
@GestureOW
twitch.tv/gestureow
 South Korea</summary>
</plugin>


<plugin>
  <title>Q&A with Gesture </title>
  <link>plugin://plugin.video.twitch/?use_player=True&video_id=v263595927&mode=play</link>
  <thumbnail>https://bnetcmsus-a.akamaihd.net/cms/page_media/SMHDMNUINHC51512776037290.png</thumbnail>
  <summary>Q&A with Gesture</summary>
</plugin>