##########################################################################################
<thumbnail></thumbnail>
<fanart></fanart>
<summary></summary>
###########################################################################################

<plugin>
  <title>Nico Twitch</title>
  <link>
    <sublink>plugin://plugin.video.twitch/?use_player=True&channel_id=17401940&amp;&mode=play  (Live Link)</sublink>
    <sublink>plugin://plugin.video.twitch/?channel_id=117401940&amp;mode=channel_videos (VODs)</sublink>
</link>
  <summary></summary>
</plugin>
